{"cameraMode":{"drawMode":0,"name":"Shaded","section":"Shading Mode"},"sceneLighting":false,"audioPlay":false,"sceneViewState":{"showFog":true,"showMaterialUpdate":false,"showSkybox":false,"showFlares":true,"showImageEffects":true,"showParticleSystems":true,"showVisualEffectGraphs":true,"m_FxEnabled":true},"in2DMode":false,"pivot":{"x":-6.184700012207031,"y":4.243226051330566,"z":-8.730268478393555},"rotation":{"x":0.1701151728630066,"y":-0.024532500654459,"z":0.004236437380313873,"w":0.9851099848747253},"size":6.719597339630127,"orthographic":true}